LICENSE
MANIFEST.in
README
README.md
setup.cfg
setup.py
pyiArduinoI2Cled/WString.cpp
pyiArduinoI2Cled/WString.h
pyiArduinoI2Cled/__init__.py
pyiArduinoI2Cled/dtostrf.cpp
pyiArduinoI2Cled/dtostrf.h
pyiArduinoI2Cled/iarduino_I2C_4LED.cpp
pyiArduinoI2Cled/iarduino_I2C_4LED.h
pyiArduinoI2Cled/iarduino_I2C_4LED.pxd
pyiArduinoI2Cled/iarduino_I2C_PI.cpp
pyiArduinoI2Cled/iarduino_I2C_PI.h
pyiArduinoI2Cled/itoa.cpp
pyiArduinoI2Cled/itoa.h
pyiArduinoI2Cled/pyiArduinoI2Cled.cpp
pyiArduinoI2Cled/pyiArduinoI2Cled.pyx
pyiArduinoI2Cled/setup.py
pyiArduinoI2Cled.egg-info/PKG-INFO
pyiArduinoI2Cled.egg-info/SOURCES.txt
pyiArduinoI2Cled.egg-info/dependency_links.txt
pyiArduinoI2Cled.egg-info/top_level.txt
pyiArduinoI2Cled/cpp/FindDevices.cpp
pyiArduinoI2Cled/cpp/NewAddress.cpp
pyiArduinoI2Cled/cpp/ShowMillis.cpp
pyiArduinoI2Cled/cpp/ShowOptions.cpp
pyiArduinoI2Cled/cpp/ShowTime.cpp
pyiArduinoI2Cled/examples/Demo3x.py
pyiArduinoI2Cled/examples/FindDevices.py
pyiArduinoI2Cled/examples/ShowMillis.py
pyiArduinoI2Cled/examples/ShowOptions.py
pyiArduinoI2Cled/examples/ShowTime.py
pyiArduinoI2Cled/examples/newAddress.py