Metadata-Version: 2.1
Name: pyiArduinoI2Cled
Version: 1.1.2
Summary: iarduino.ru module for Raspberry Pi
Home-page: http://github.com/tremaru/pyiArduinoI2Cled
Author: iarduino.ru
Author-email: shop@iarduino.ru
License: MIT
Classifier: Programming Language :: Python :: 3
License-File: LICENSE
